Metadata-Version: 2.4
Name: django_good_otp
Version: 2.0.5
Summary: Yet Another Implementation of One-Time-Password-Authentication for Django
Home-page: https://github.com/hiroaki-yamamoto/django-good-otp
License: MIT
Keywords: python,OTP,Django
Classifier: License :: OSI Approved :: MIT License
Classifier: Programming Language :: Python :: 2
Classifier: Programming Language :: Python :: 3
License-File: LICENSE.md
Requires-Dist: pyotp
Requires-Dist: qrcode
Requires-Dist: django>=1.10
Requires-Dist: jinja2
Dynamic: classifier
Dynamic: description
Dynamic: description-content-type
Dynamic: home-page
Dynamic: keywords
Dynamic: license
Dynamic: license-file
Dynamic: requires-dist
Dynamic: summary
